Metadata-Version: 2.1
Name: DataScouter
Version: 1.1.0
Summary: An AI-powered dataset search engine across Hugging Face, Kaggle, and Google Dataset Search
Home-page: https://github.com/arun6832/DataScouter
Author: Arun M
Author-email: arunpappulli@gmail.com
Classifier: Programming Language :: Python :: 3
Classifier: License :: OSI Approved :: MIT License
Classifier: Operating System :: OS Independent
Requires-Python: >=3.7
